USL_lib_beta/__init__.py
usl_lib_beta-2025.6.2.dist-info/licenses/LICENSE
usl_lib_beta-2025.6.2.dist-info/METADATA
usl_lib_beta-2025.6.2.dist-info/WHEEL
usl_lib_beta-2025.6.2.dist-info/top_level.txt
usl_lib_beta-2025.6.2.dist-info/RECORD
