Metadata-Version: 2.4
Name: USL_lib_beta
Version: 2025.6.2
Summary: Some useful functions for USL(ultra-stable laser)
Author-email: zxq985 <zxq985160104@163.com>
Project-URL: Repository, https://github.com/ShinetingChu/USL_lib_beta
Project-URL: Pypi, https://pypi.org/project/USL-lib-beta/
Classifier: Programming Language :: Python :: 3
Classifier: License :: OSI Approved :: MIT License
Requires-Python: >=3.8
License-File: LICENSE
Dynamic: license-file
